chimp_osc/__init__.py
chimp_osc/chimp.py
chimp_osc/chimp_osc_interface.py
chimp_osc/chimp_ui.py
chimp_osc/console/__init__.py
chimp_osc/console/button.py
chimp_osc/console/encoder.py
chimp_osc/console/executor.py
chimp_osc/console/executor_page.py
chimp_osc/console/fader.py
chimp_osc/console/fader_page.py
chimp_osc/console/led_button.py
chimp_osc/console/master.py
chimp_osc/console/programmer.py
chimp_osc/controllers/__init__.py
chimp_osc/controllers/xbox.py
chimp_osc/controllers/base/__init__.py
chimp_osc/controllers/base/controller.py
chimp_osc/controllers/base/inputs.py
chimp_osc/controllers/base/logiccontroller.py
chimp_osc/controllers/base/manager.py
chimp_osc/ui/__init__.py
chimp_osc/ui/banana_wing.py
chimp_osc/ui/main_console.py
chimp_osc/ui/virtual_ui.py
chimp_osc/ui/elements/__init__.py
chimp_osc/ui/elements/button_ui.py
chimp_osc/ui/elements/encoder_ui.py
chimp_osc/ui/elements/executor_ui.py
chimp_osc/ui/elements/fader_ui.py
chimp_osc/ui/elements/home_ui.py
chimp_osc/ui/elements/led_button_ui.py
chimp_osc/ui/elements/master_ui.py
chimp_osc/ui/elements/programmer_ui.py
chimp_osc/ui/elements/select_feature_ui.py
chimp_osc/ui/style/__init__.py
chimp_osc/ui/style/button.py
chimp_osc/ui/style/fader.py
chimp_osc/ui/style/grid.py
chimp_osc-0.2.0.dist-info/METADATA
chimp_osc-0.2.0.dist-info/WHEEL
chimp_osc-0.2.0.dist-info/top_level.txt
chimp_osc-0.2.0.dist-info/RECORD
