Metadata-Version: 2.4
Name: chimp-osc
Version: 0.2.0
Summary: Wrapper for OSC of the Infinity Chimp Lighting Console
Author-email: David Dietrich <info@davelight.de>
Keywords: osc,infinity,chimp,lighting
Classifier: Development Status :: 3 - Alpha
Classifier: Intended Audience :: Developers
Classifier: License :: Freely Distributable
Classifier: Programming Language :: Python :: 3
Requires-Python: >=3.12
Requires-Dist: python-osc
Provides-Extra: ui
Requires-Dist: nicegui; extra == "ui"
Provides-Extra: controller
Requires-Dist: pygame; extra == "controller"
Provides-Extra: full
Requires-Dist: nicegui; extra == "full"
Requires-Dist: pygame; extra == "full"
